jemail/__init__.py
jemail/apps.py
jemail/models.py
jemail/py.typed
jemail/settings.py
jemail/migrations/0001_initial.py
jemail/migrations/__init__.py
jemail-0.1a6.dist-info/METADATA
jemail-0.1a6.dist-info/WHEEL
jemail-0.1a6.dist-info/licenses/LICENSE
jemail-0.1a6.dist-info/RECORD
