Metadata-Version: 2.3
Name: jemail
Version: 0.1a6
Summary: Django app to store emails in db
Project-URL: Repository, https://github.com/kotify/jemail
Project-URL: Changelog, https://github.com/kotify/jemail/blob/main/CHANGELOG.md
Author-email: Konstantin Alekseev <mail@kalekseev.com>
License-Expression: MIT
License-File: LICENSE
Keywords: django,email
Classifier: Development Status :: 4 - Beta
Classifier: Environment :: Web Environment
Classifier: Framework :: Django :: 4.2
Classifier: Framework :: Django :: 5.0
Classifier: Framework :: Django :: 5.1
Classifier: Intended Audience :: Developers
Classifier: License :: OSI Approved :: MIT License
Classifier: Operating System :: OS Independent
Classifier: Programming Language :: Python :: 3.9
Classifier: Programming Language :: Python :: 3.10
Classifier: Programming Language :: Python :: 3.11
Classifier: Programming Language :: Python :: 3.12
Classifier: Programming Language :: Python :: 3.13
Classifier: Typing :: Typed
Requires-Python: >=3.9
Requires-Dist: django-anymail
Requires-Dist: django>=4.2
Requires-Dist: html2text
Provides-Extra: dev
Requires-Dist: django-stubs; extra == 'dev'
Requires-Dist: mypy; extra == 'dev'
Requires-Dist: pdbpp; extra == 'dev'
Requires-Dist: pre-commit; extra == 'dev'
Requires-Dist: ruff; extra == 'dev'
Provides-Extra: test
Requires-Dist: pytest; extra == 'test'
Requires-Dist: pytest-cov; extra == 'test'
Requires-Dist: pytest-django; extra == 'test'
